pysimpledmx/__init__.py
pysimpledmx/pysimpledmx.py
pysimpledmx-0.1.1.dist-info/DESCRIPTION.rst
pysimpledmx-0.1.1.dist-info/METADATA
pysimpledmx-0.1.1.dist-info/RECORD
pysimpledmx-0.1.1.dist-info/WHEEL
pysimpledmx-0.1.1.dist-info/metadata.json
pysimpledmx-0.1.1.dist-info/top_level.txt
