Metadata-Version: 2.0
Name: pysimpledmx
Version: 0.1.1
Summary: simple dmx control for the Enttec DMX USB Pro
Home-page: https://github.com/c0z3n/pySimpleDMX
Author: c0z3n
Author-email: UNKNOWN
License: GPLV3
Platform: UNKNOWN
Classifier: Programming Language :: Python
Classifier: Programming Language :: Python :: 2
Classifier: Programming Language :: Python :: 2.7
Classifier: Intended Audience :: Other Audience
Classifier: Topic :: Artistic Software
Requires-Dist: pyserial
